pybot/__init__.py
pybot/world/__init__.py
pybot/world/world.py
pybotic/__init__.py
pybotic/world/__init__.py
pybotic/world/world.py
pybotic-0.0.1.dist-info/LICENSE
pybotic-0.0.1.dist-info/METADATA
pybotic-0.0.1.dist-info/WHEEL
pybotic-0.0.1.dist-info/top_level.txt
pybotic-0.0.1.dist-info/RECORD
