Metadata-Version: 2.1
Name: pybotic
Version: 0.0.1
Summary: pyBot
Home-page: https://github.com/robo-bootcamp/pyBot
Author: Arun Joseph | Gunjan Patil
Author-email: arunjoseph.eng@gmail.com
License: UNKNOWN
Platform: UNKNOWN
Classifier: Development Status :: 1 - Planning
Classifier: Intended Audience :: Science/Research
Classifier: License :: OSI Approved :: MIT License
Classifier: Framework :: Robot Framework
Classifier: Programming Language :: Python :: 3
Classifier: Programming Language :: Python :: 3.5
Classifier: Programming Language :: Python :: 3.6
Classifier: Programming Language :: Python :: 3.7
Classifier: Programming Language :: Python :: 3.8
Classifier: Operating System :: OS Independent
